pytest_opentelemetry/__init__.py
pytest_opentelemetry/instrumentation.py
pytest_opentelemetry/plugin.py
pytest_opentelemetry/py.typed
pytest_opentelemetry/resource.py
pytest_opentelemetry-1.1.0.dist-info/licenses/LICENSE
pytest_opentelemetry-1.1.0.dist-info/METADATA
pytest_opentelemetry-1.1.0.dist-info/WHEEL
pytest_opentelemetry-1.1.0.dist-info/entry_points.txt
pytest_opentelemetry-1.1.0.dist-info/top_level.txt
pytest_opentelemetry-1.1.0.dist-info/RECORD
