Metadata-Version: 2.4
Name: pytest-opentelemetry
Version: 1.1.0
Summary: A pytest plugin for instrumenting test runs via OpenTelemetry
Home-page: https://github.com/chrisguidry/pytest-opentelemetry
Author: Chris Guidry
Author-email: chris@theguidrys.us
Project-URL: Bug Tracker, https://github.com/chrisguidry/pytest-opentelemetry/issues
Classifier: Programming Language :: Python :: 3
Classifier: License :: OSI Approved :: MIT License
Classifier: Operating System :: OS Independent
Classifier: Framework :: Pytest
Requires-Python: >=3.8
License-File: LICENSE
Requires-Dist: opentelemetry-api
Requires-Dist: opentelemetry-container-distro
Requires-Dist: opentelemetry-sdk
Requires-Dist: opentelemetry-semantic-conventions
Requires-Dist: pytest
Provides-Extra: dev
Requires-Dist: black; extra == "dev"
Requires-Dist: build; extra == "dev"
Requires-Dist: flake8; extra == "dev"
Requires-Dist: flake8-black; extra == "dev"
Requires-Dist: isort; extra == "dev"
Requires-Dist: mypy; extra == "dev"
Requires-Dist: pre-commit; extra == "dev"
Requires-Dist: pytest; extra == "dev"
Requires-Dist: pytest-cov; extra == "dev"
Requires-Dist: pytest-xdist; extra == "dev"
Requires-Dist: twine; extra == "dev"
Dynamic: license-file
